tree_sitter_sdml/__init__.py
tree_sitter_sdml/__init__.pyi
tree_sitter_sdml/_binding.abi3.so
tree_sitter_sdml/binding.c
tree_sitter_sdml/py.typed
tree_sitter_sdml/queries/folds.scm
tree_sitter_sdml/queries/highlights.scm
tree_sitter_sdml/queries/indent.scm
tree_sitter_sdml/queries/injections.scm
tree_sitter_sdml/queries/locals.scm
tree_sitter_sdml/queries/tags.scm
tree_sitter_sdml-0.4.14.dist-info/licenses/LICENSE
tree_sitter_sdml-0.4.14.dist-info/METADATA
tree_sitter_sdml-0.4.14.dist-info/WHEEL
tree_sitter_sdml-0.4.14.dist-info/top_level.txt
tree_sitter_sdml-0.4.14.dist-info/RECORD
