Metadata-Version: 2.4
Name: tree-sitter-sdml
Version: 0.4.14
Summary: SDML grammar for tree-sitter
License-Expression: Apache-2.0
Project-URL: Homepage, https://github.com/tree-sitter/tree-sitter-sdml
Keywords: incremental,parsing,tree-sitter,sdml
Classifier: Intended Audience :: Developers
Classifier: Topic :: Software Development :: Compilers
Classifier: Topic :: Text Processing :: Linguistic
Classifier: Typing :: Typed
Requires-Python: >=3.9
License-File: LICENSE
Provides-Extra: core
Requires-Dist: tree-sitter~=0.24; extra == "core"
Dynamic: license-file
